error_helper/__init__.py
error_helper/py.typed
error_helper-1.5.dist-info/METADATA
error_helper-1.5.dist-info/WHEEL
error_helper-1.5.dist-info/licenses/LICENSE
error_helper-1.5.dist-info/RECORD
