Metadata-Version: 2.4
Name: error-helper
Version: 1.5
Summary: Minimalistic python module to print colorful messages
Project-URL: Homepage, https://github.com/30350n/error_helper
Author-email: Bobbe <mail@30350n.de>
License-Expression: MIT
License-File: LICENSE
Classifier: Development Status :: 5 - Production/Stable
Classifier: Environment :: Console
Classifier: License :: OSI Approved :: MIT License
Classifier: Operating System :: OS Independent
Classifier: Programming Language :: Python :: 3
Requires-Python: >=3.6
